qck.py
qck-2025.8.28.dist-info/licenses/LICENSE
qck-2025.8.28.dist-info/METADATA
qck-2025.8.28.dist-info/WHEEL
qck-2025.8.28.dist-info/entry_points.txt
qck-2025.8.28.dist-info/top_level.txt
qck-2025.8.28.dist-info/RECORD
