Metadata-Version: 2.4
Name: qck
Version: 2025.8.28
Summary: CLI to conveniently run DuckDB SQL scripts with support for templating
Home-page: https://github.com/dnouri/qck
Author: Daniel Nouri
License: MIT
Classifier: Programming Language :: Python :: 3
Classifier: Programming Language :: SQL
Classifier: Topic :: Database :: Front-Ends
License-File: LICENSE
Requires-Dist: click
Requires-Dist: duckdb
Requires-Dist: jinja2
Requires-Dist: pandas
Requires-Dist: tabulate
Provides-Extra: devel
Requires-Dist: black; extra == "devel"
Requires-Dist: ruff; extra == "devel"
Dynamic: license-file
